bibliomancer/__init__.py
bibliomancer/cli.py
bibliomancer/datamodel/__init__.py
bibliomancer/datamodel/biblio.py
bibliomancer/datamodel/biblio.yaml
bibliomancer/datamodel/biblio_td.py
bibliomancer/datamodel/enums.py
bibliomancer/datamodel/from_paperpile.tr.yaml
bibliomancer/datamodel/paperpile.py
bibliomancer/datamodel/paperpile.yaml
bibliomancer/enricher.py
bibliomancer/eutils.py
bibliomancer/formatter.py
bibliomancer/io.py
bibliomancer/mapper.py
bibliomancer/mergeutil.py
bibliomancer/templates/__init__.py
bibliomancer/templates/default.markdown.jinja2
bibliomancer/utilities.py
bibliomancer/validator.py
bibliomancer-0.1.0.dist-info/LICENSE
bibliomancer-0.1.0.dist-info/METADATA
bibliomancer-0.1.0.dist-info/WHEEL
bibliomancer-0.1.0.dist-info/entry_points.txt
bibliomancer-0.1.0.dist-info/RECORD
